README.txt
setup.py
collective/__init__.py
collective.collage.innerfade.egg-info/PKG-INFO
collective.collage.innerfade.egg-info/SOURCES.txt
collective.collage.innerfade.egg-info/dependency_links.txt
collective.collage.innerfade.egg-info/entry_points.txt
collective.collage.innerfade.egg-info/namespace_packages.txt
collective.collage.innerfade.egg-info/not-zip-safe
collective.collage.innerfade.egg-info/requires.txt
collective.collage.innerfade.egg-info/top_level.txt
collective/collage/__init__.py
collective/collage/innerfade/__init__.py
collective/collage/innerfade/browser.py
collective/collage/innerfade/configure.zcml
collective/collage/innerfade/tests.py
collective/collage/innerfade/templates/innerfade.pt
docs/HISTORY.txt
docs/INSTALL.txt
docs/LICENSE.GPL
docs/LICENSE.txt