Metadata-Version: 1.0
Name: collective.collage.innerfade
Version: 1.0-final
Summary: Collage integration of the Innerfade module
Home-page: http://svn.plone.org/svn/collective/
Author: UNKNOWN
Author-email: UNKNOWN
License: GPL
Platform: UNKNOWN
Classifier: Framework :: Plone
Classifier: Programming Language :: Python
